README.md
setup.py
CoStrOb/__init__.py
CoStrOb.egg-info/PKG-INFO
CoStrOb.egg-info/SOURCES.txt
CoStrOb.egg-info/dependency_links.txt
CoStrOb.egg-info/top_level.txt