Metadata-Version: 2.1
Name: CoStrOb
Version: 0.0.1
Summary: time multiple tasks for optimized usage of recourses
Home-page: UNKNOWN
Author: Fabian Becker
Author-email: fab.becker@protonmail.com
License: UNKNOWN
Platform: UNKNOWN
Classifier: Programming Language :: Python :: 3
Classifier: License :: OSI Approved :: GNU General Public License v3 (GPLv3)
Classifier: Operating System :: OS Independent
